esa_python_sdk/__init__.py
esa_python_sdk-0.0.31.dist-info/LICENSE
esa_python_sdk-0.0.31.dist-info/METADATA
esa_python_sdk-0.0.31.dist-info/WHEEL
esa_python_sdk-0.0.31.dist-info/top_level.txt
esa_python_sdk-0.0.31.dist-info/RECORD
